README.md
setup.py
tinydataset/__init__.py
tinydataset.egg-info/PKG-INFO
tinydataset.egg-info/SOURCES.txt
tinydataset.egg-info/dependency_links.txt
tinydataset.egg-info/top_level.txt