Metadata-Version: 2.1
Name: tinydataset
Version: 0.1.2
Summary: tinydataset is two dememsional array, which implements with a list of dictionaries, generated by mysql query action generally.
Home-page: https://github.com/jamesqin-cn/tinydataset
Author: jamesqin
Author-email: jamesqin@vip.qq.com
License: MIT
Platform: any
Classifier: Intended Audience :: Developers
Classifier: Operating System :: OS Independent
Classifier: Topic :: Utilities
Classifier: Topic :: Software Development :: Libraries :: Python Modules
Classifier: Programming Language :: Python
Classifier: Programming Language :: Python :: 2
Classifier: Programming Language :: Python :: 2.7
Classifier: Programming Language :: Python :: 3
Classifier: Programming Language :: Python :: 3.7
